kotlin version: 2.0.21
error message: org.jetbrains.kotlin.codegen.CompilationException: Back-end (JVM) Internal error: Couldn't transform method node:
PantallaArqueoCaja (Landroidx/navigation/NavController;Ljava/lang/String;Landroidx/compose/runtime/Composer;I)V:
  @Landroidx/compose/runtime/Composable;() // invisible
  @Landroidx/compose/runtime/ComposableTarget;(applier="androidx.compose.ui.UiComposable") // invisible
    // annotable parameter count: 4 (visible)
    // annotable parameter count: 4 (invisible)
    @Lorg/jetbrains/annotations/NotNull;() // invisible, parameter 0
    @Lorg/jetbrains/annotations/NotNull;() // invisible, parameter 1
    @Lorg/jetbrains/annotations/Nullable;() // invisible, parameter 2
   L0
    ALOAD 0
    LDC "navController"
    INVOKESTATIC kotlin/jvm/internal/Intrinsics.checkNotNullParameter (Ljava/lang/Object;Ljava/lang/String;)V
    ALOAD 1
    LDC "mercadilloId"
    INVOKESTATIC kotlin/jvm/internal/Intrinsics.checkNotNullParameter (Ljava/lang/Object;Ljava/lang/String;)V
   L1
    LINENUMBER 34 L1
    ALOAD 2
    LDC 91271578
    INVOKEINTERFACE androidx/compose/runtime/Composer.startRestartGroup (I)Landroidx/compose/runtime/Composer; (itf)
    ASTORE 2
    ALOAD 2
    LDC "C(PantallaArqueoCaja)P(1)34@1514L7,35@1537L42,36@1610L58,37@1689L16,38@1761L16,41@1836L45,42@1908L32,44@1975L187,44@1946L216,51@2180L24,52@2231L34,53@2287L34,56@2354L520,69@2881L5347,55@2327L5901:PantallaArqueoCaja.kt#ia6z34"
    INVOKESTATIC androidx/compose/runtime/ComposerKt.sourceInformation (Landroidx/compose/runtime/Composer;Ljava/lang/String;)V
    ILOAD 3
    ISTORE 4
   L2
    ILOAD 3
    BIPUSH 6
    IAND
    IFNE L3
    ILOAD 4
    ALOAD 2
    ALOAD 0
    INVOKEINTERFACE androidx/compose/runtime/Composer.changedInstance (Ljava/lang/Object;)Z (itf)
    IFEQ L4
    ICONST_4
    GOTO L5
   L4
    ICONST_2
   L5
    IOR
    ISTORE 4
   L3
    ILOAD 3
    BIPUSH 48
    IAND
    IFNE L6
    ILOAD 4
    ALOAD 2
    ALOAD 1
    INVOKEINTERFACE androidx/compose/runtime/Composer.changed (Ljava/lang/Object;)Z (itf)
    IFEQ L7
    BIPUSH 32
    GOTO L8
   L7
    BIPUSH 16
   L8
    IOR
    ISTORE 4
   L6
    ILOAD 4
    BIPUSH 19
    IAND
    BIPUSH 18
    IF_ICMPNE L9
    ALOAD 2
    INVOKEINTERFACE androidx/compose/runtime/Composer.getSkipping ()Z (itf)
    IFNE L10
   L9
    INVOKESTATIC androidx/compose/runtime/ComposerKt.isTraceInProgress ()Z
    IFEQ L11
    LDC 91271578
    ILOAD 4
    ICONST_M1
    LDC "es.nuskysoftware.marketsales.ui.pantallas.arqueo.PantallaArqueoCaja (PantallaArqueoCaja.kt:33)"
    INVOKESTATIC androidx/compose/runtime/ComposerKt.traceEventStart (IIILjava/lang/String;)V
   L11
    LINENUMBER 35 L11
    INVOKESTATIC androidx/compose/ui/platform/AndroidCompositionLocals_androidKt.getLocalContext ()Landroidx/compose/runtime/ProvidableCompositionLocal;
    CHECKCAST androidx/compose/runtime/CompositionLocal
    ASTORE 6
    ICONST_0
    ISTORE 7
    NOP
   L12
    ICONST_0
    ISTORE 8
   L13
    ALOAD 2
    LDC 2023513938
    LDC "CC(<get-current>):CompositionLocal.kt#9igjgp"
   L14
    LINENUMBER 422 L14
    INVOKESTATIC androidx/compose/runtime/ComposerKt.sourceInformationMarkerStart (Landroidx/compose/runtime/Composer;ILjava/lang/String;)V
    ALOAD 2
    ALOAD 6
    INVOKEINTERFACE androidx/compose/runtime/Composer.consume (Landroidx/compose/runtime/CompositionLocal;)Ljava/lang/Object; (itf)
    ASTORE 9
    ALOAD 2
    INVOKESTATIC androidx/compose/runtime/ComposerKt.sourceInformationMarkerEnd (Landroidx/compose/runtime/Composer;)V
    ALOAD 9
    NOP
    GOTO L15
   L15
    LINENUMBER 35 L15
    CHECKCAST android/content/Context
    ASTORE 5
   L16
    ALOAD 2
    LDC 1129912355
    INVOKEINTERFACE androidx/compose/runtime/Composer.startReplaceGroup (I)V (itf)
    ALOAD 2
    LDC "CC(remember):PantallaArqueoCaja.kt#9igjgp"
    INVOKESTATIC androidx/compose/runtime/ComposerKt.sourceInformation (Landroidx/compose/runtime/Composer;Ljava/lang/String;)V
    ALOAD 2
    ASTORE 8
    NOP
    ICONST_0
    ISTORE 9
   L17
    LINENUMBER 36 L17
    NOP
   L18
    ICONST_0
    ISTORE 10
   L19
    LINENUMBER 423 L19
    ALOAD 8
    INVOKEINTERFACE androidx/compose/runtime/Composer.rememberedValue ()Ljava/lang/Object; (itf)
    ASTORE 11
   L20
    ICONST_0
    ISTORE 12
   L21
    LINENUMBER 424 L21
    ILOAD 9
    POP
    ALOAD 11
    GETSTATIC androidx/compose/runtime/Composer.Companion : Landroidx/compose/runtime/Composer$Companion;
    INVOKEVIRTUAL androidx/compose/runtime/Composer$Companion.getEmpty ()Ljava/lang/Object;
    IF_ACMPNE L22
   L23
    LINENUMBER 425 L23
    NOP
   L24
    ICONST_0
    ISTORE 13
   L25
    LINENUMBER 36 L25
    NEW es/nuskysoftware/marketsales/data/repository/MercadilloRepository
    DUP
    ALOAD 5
    INVOKESPECIAL es/nuskysoftware/marketsales/data/repository/MercadilloRepository.<init> (Landroid/content/Context;)V
    NOP
    GOTO L26
   L26
   L27
    LINENUMBER 425 L27
    ASTORE 14
   L28
    LINENUMBER 426 L28
    ALOAD 8
    ALOAD 14
    INVOKEINTERFACE androidx/compose/runtime/Composer.updateRememberedValue (Ljava/lang/Object;)V (itf)
   L29
    LINENUMBER 427 L29
    ALOAD 14
   L30
    GOTO L31
   L22
    LINENUMBER 428 L22
    ALOAD 11
   L31
    LINENUMBER 423 L31
    NOP
   L32
    LINENUMBER 423 L32
    NOP
    GOTO L33
   L33
    LINENUMBER 36 L33
    CHECKCAST es/nuskysoftware/marketsales/data/repository/MercadilloRepository
    ASTORE 7
   L34
    ALOAD 2
    INVOKEINTERFACE androidx/compose/runtime/Composer.endReplaceGroup ()V (itf)
    ALOAD 7
   L35
    ASTORE 6
   L36
    LINENUMBER 37 L36
    NEW es/nuskysoftware/marketsales/ui/viewmodel/ArqueoViewModelFactory
    DUP
    ALOAD 5
    ALOAD 6
    INVOKESPECIAL es/nuskysoftware/marketsales/ui/viewmodel/ArqueoViewModelFactory.<init> (Landroid/content/Context;Les/nuskysoftware/marketsales/data/repository/MercadilloRepository;)V
    CHECKCAST androidx/lifecycle/ViewModelProvider$Factory
    ASTORE 10
    ICONST_0
    ISTORE 12
    NOP
   L37
    ICONST_0
    ISTORE 13
   L38
    ALOAD 2
    LDC 1729797275
    LDC "CC(viewModel)P(3,2,1)56@2573L7,67@2980L63:ViewModel.kt#3tja67"
   L39
    LINENUMBER 429 L39
    INVOKESTATIC androidx/compose/runtime/ComposerKt.sourceInformationMarkerStart (Landroidx/compose/runtime/Composer;ILjava/lang/String;)V
   L40
    LINENUMBER 430 L40
    GETSTATIC androidx/lifecycle/viewmodel/compose/LocalViewModelStoreOwner.INSTANCE : Landroidx/lifecycle/viewmodel/compose/LocalViewModelStoreOwner;
    ALOAD 2
    BIPUSH 6
    INVOKEVIRTUAL androidx/lifecycle/viewmodel/compose/LocalViewModelStoreOwner.getCurrent (Landroidx/compose/runtime/Composer;I)Landroidx/lifecycle/ViewModelStoreOwner;
    DUP
    IFNONNULL L41
    POP
    ICONST_0
    ISTORE 14
   L42
    LDC "No ViewModelStoreOwner was provided via LocalViewModelStoreOwner"
   L43
    LINENUMBER 431 L43
    NOP
   L44
    LINENUMBER 430 L44
    ASTORE 14
    NEW java/lang/IllegalStateException
    DUP
    ALOAD 14
    INVOKEVIRTUAL java/lang/Object.toString ()Ljava/lang/String;
    INVOKESPECIAL java/lang/IllegalStateException.<init> (Ljava/lang/String;)V
    ATHROW
   L41
    ASTORE 8
   L45
    LINENUMBER 433 L45
    ACONST_NULL
    ASTORE 9
   L46
    LINENUMBER 436 L46
    ALOAD 8
    INSTANCEOF androidx/lifecycle/HasDefaultViewModelProviderFactory
    IFEQ L47
   L48
    LINENUMBER 437 L48
    ALOAD 8
    CHECKCAST androidx/lifecycle/HasDefaultViewModelProviderFactory
    INVOKEINTERFACE androidx/lifecycle/HasDefaultViewModelProviderFactory.getDefaultViewModelCreationExtras ()Landroidx/lifecycle/viewmodel/CreationExtras; (itf)
    GOTO L49
   L47
    LINENUMBER 439 L47
    GETSTATIC androidx/lifecycle/viewmodel/CreationExtras$Empty.INSTANCE : Landroidx/lifecycle/viewmodel/CreationExtras$Empty;
    CHECKCAST androidx/lifecycle/viewmodel/CreationExtras
   L49
    ASTORE 11
   L50
    LDC Les/nuskysoftware/marketsales/ui/viewmodel/ArqueoViewModel;.class
    INVOKESTATIC kotlin/jvm/internal/Reflection.getOrCreateKotlinClass (Ljava/lang/Class;)Lkotlin/reflect/KClass;
   L51
    LINENUMBER 429 L51
    ALOAD 8
    ALOAD 9
    ALOAD 10
    ALOAD 11
    ALOAD 2
    BIPUSH 112
    ILOAD 12
    ICONST_3
    ISHL
    IAND
    SIPUSH 896
    ILOAD 12
    ICONST_3
    ISHL
    IAND
    IOR
    SIPUSH 7168
    ILOAD 12
    ICONST_3
    ISHL
    IAND
    IOR
    LDC 57344
    ILOAD 12
    ICONST_3
    ISHL
    IAND
    IOR
    ICONST_0
    INVOKESTATIC androidx/lifecycle/viewmodel/compose/ViewModelKt.viewModel (Lkotlin/reflect/KClass;Landroidx/lifecycle/ViewModelStoreOwner;Ljava/lang/String;Landroidx/lifecycle/ViewModelProvider$Factory;Landroidx/lifecycle/viewmodel/CreationExtras;Landroidx/compose/runtime/Composer;II)Landroidx/lifecycle/ViewModel;
    ASTORE 15
    ALOAD 2
    INVOKESTATIC androidx/compose/runtime/ComposerKt.sourceInformationMarkerEnd (Landroidx/compose/runtime/Composer;)V
    ALOAD 15
    NOP
    GOTO L52
   L52
    LINENUMBER 37 L52
    CHECKCAST es/nuskysoftware/marketsales/ui/viewmodel/ArqueoViewModel
    ASTORE 7
   L53
    LINENUMBER 38 L53
    ALOAD 7
    INVOKEVIRTUAL es/nuskysoftware/marketsales/ui/viewmodel/ArqueoViewModel.getUi ()Lkotlinx/coroutines/flow/StateFlow;
    ACONST_NULL
    ALOAD 2
    ICONST_0
    ICONST_1
    INVOKESTATIC androidx/compose/runtime/SnapshotStateKt.collectAsState (Lkotlinx/coroutines/flow/StateFlow;Lkotlin/coroutines/CoroutineContext;Landroidx/compose/runtime/Composer;II)Landroidx/compose/runtime/State;
    ASTORE 8
   L54
    LINENUMBER 39 L54
    GETSTATIC es/nuskysoftware/marketsales/utils/ConfigurationManager.INSTANCE : Les/nuskysoftware/marketsales/utils/ConfigurationManager;
    INVOKEVIRTUAL es/nuskysoftware/marketsales/utils/ConfigurationManager.getIdioma ()Lkotlinx/coroutines/flow/StateFlow;
    ACONST_NULL
    ALOAD 2
    ICONST_0
    ICONST_1
    INVOKESTATIC androidx/compose/runtime/SnapshotStateKt.collectAsState (Lkotlinx/coroutines/flow/StateFlow;Lkotlin/coroutines/CoroutineContext;Landroidx/compose/runtime/Composer;II)Landroidx/compose/runtime/State;
    ASTORE 9
   L55
    ALOAD 2
    LDC 1129921926
    INVOKEINTERFACE androidx/compose/runtime/Composer.startReplaceGroup (I)V (itf)
    ALOAD 2
    LDC "CC(remember):PantallaArqueoCaja.kt#9igjgp"
    INVOKESTATIC androidx/compose/runtime/ComposerKt.sourceInformation (Landroidx/compose/runtime/Composer;Ljava/lang/String;)V
    ALOAD 2
    ASTORE 12
    NOP
    ICONST_0
    ISTORE 13
   L56
    LINENUMBER 42 L56
    NOP
   L57
    ICONST_0
    ISTORE 14
   L58
    LINENUMBER 440 L58
    ALOAD 12
    INVOKEINTERFACE androidx/compose/runtime/Composer.rememberedValue ()Ljava/lang/Object; (itf)
    ASTORE 15
   L59
    ICONST_0
    ISTORE 16
   L60
    LINENUMBER 441 L60
    ILOAD 13
    POP
    ALOAD 15
    GETSTATIC androidx/compose/runtime/Composer.Companion : Landroidx/compose/runtime/Composer$Companion;
    INVOKEVIRTUAL androidx/compose/runtime/Composer$Companion.getEmpty ()Ljava/lang/Object;
    IF_ACMPNE L61
   L62
    LINENUMBER 442 L62
    NOP
   L63
    ICONST_0
    ISTORE 17
   L64
    LINENUMBER 42 L64
    GETSTATIC es/nuskysoftware/marketsales/data/local/database/AppDatabase.Companion : Les/nuskysoftware/marketsales/data/local/database/AppDatabase$Companion;
    ALOAD 5
    INVOKEVIRTUAL es/nuskysoftware/marketsales/data/local/database/AppDatabase$Companion.getDatabase (Landroid/content/Context;)Les/nuskysoftware/marketsales/data/local/database/AppDatabase;
    NOP
    GOTO L65
   L65
   L66
    LINENUMBER 442 L66
    ASTORE 18
   L67
    LINENUMBER 443 L67
    ALOAD 12
    ALOAD 18
    INVOKEINTERFACE androidx/compose/runtime/Composer.updateRememberedValue (Ljava/lang/Object;)V (itf)
   L68
    LINENUMBER 444 L68
    ALOAD 18
   L69
    GOTO L70
   L61
    LINENUMBER 445 L61
    ALOAD 15
   L70
    LINENUMBER 440 L70
    NOP
   L71
    LINENUMBER 440 L71
    NOP
    GOTO L72
   L72
    LINENUMBER 42 L72
    CHECKCAST es/nuskysoftware/marketsales/data/local/database/AppDatabase
    ASTORE 11
   L73
    ALOAD 2
    INVOKEINTERFACE androidx/compose/runtime/Composer.endReplaceGroup ()V (itf)
    ALOAD 11
   L74
    ASTORE 10
   L75
    ALOAD 2
    LDC 1129924217
    INVOKEINTERFACE androidx/compose/runtime/Composer.startReplaceGroup (I)V (itf)
    ALOAD 2
    LDC "CC(remember):PantallaArqueoCaja.kt#9igjgp"
    INVOKESTATIC androidx/compose/runtime/ComposerKt.sourceInformation (Landroidx/compose/runtime/Composer;Ljava/lang/String;)V
    ALOAD 2
    ASTORE 13
    NOP
    ICONST_0
    ISTORE 14
   L76
    LINENUMBER 43 L76
    NOP
   L77
    ICONST_0
    ISTORE 15
   L78
    LINENUMBER 446 L78
    ALOAD 13
    INVOKEINTERFACE androidx/compose/runtime/Composer.rememberedValue ()Ljava/lang/Object; (itf)
    ASTORE 16
   L79
    ICONST_0
    ISTORE 17
   L80
    LINENUMBER 447 L80
    ILOAD 14
    POP
    ALOAD 16
    GETSTATIC androidx/compose/runtime/Composer.Companion : Landroidx/compose/runtime/Composer$Companion;
    INVOKEVIRTUAL androidx/compose/runtime/Composer$Companion.getEmpty ()Ljava/lang/Object;
    IF_ACMPNE L81
   L82
    LINENUMBER 448 L82
    NOP
   L83
    ICONST_0
    ISTORE 18
   L84
    LINENUMBER 43 L84
    DCONST_0
    INVOKESTATIC java/lang/Double.valueOf (D)Ljava/lang/Double;
    ACONST_NULL
    ICONST_2
    ACONST_NULL
    INVOKESTATIC androidx/compose/runtime/SnapshotStateKt.mutableStateOf$default (Ljava/lang/Object;Landroidx/compose/runtime/SnapshotMutationPolicy;ILjava/lang/Object;)Landroidx/compose/runtime/MutableState;
    NOP
    GOTO L85
   L85
   L86
    LINENUMBER 448 L86
    ASTORE 18
   L87
    LINENUMBER 449 L87
    ALOAD 13
    ALOAD 18
    INVOKEINTERFACE androidx/compose/runtime/Composer.updateRememberedValue (Ljava/lang/Object;)V (itf)
   L88
    LINENUMBER 450 L88
    ALOAD 18
   L89
    GOTO L90
   L81
    LINENUMBER 451 L81
    ALOAD 16
   L90
    LINENUMBER 446 L90
    NOP
   L91
    LINENUMBER 446 L91
    NOP
    GOTO L92
   L92
    LINENUMBER 43 L92
    CHECKCAST androidx/compose/runtime/MutableState
    ASTORE 12
   L93
    ALOAD 2
    INVOKEINTERFACE androidx/compose/runtime/Composer.endReplaceGroup ()V (itf)
    ALOAD 12
   L94
    ASTORE 11
   L95
    LINENUMBER 45 L95
    ALOAD 1
    ALOAD 2
    LDC 1129926516
    INVOKEINTERFACE androidx/compose/runtime/Composer.startReplaceGroup (I)V (itf)
    ALOAD 2
    LDC "CC(remember):PantallaArqueoCaja.kt#9igjgp"
    INVOKESTATIC androidx/compose/runtime/ComposerKt.sourceInformation (Landroidx/compose/runtime/Composer;Ljava/lang/String;)V
    ALOAD 2
    ASTORE 13
    ALOAD 2
    ALOAD 7
    INVOKEINTERFACE androidx/compose/runtime/Composer.changedInstance (Ljava/lang/Object;)Z (itf)
    ILOAD 4
    BIPUSH 112
    IAND
    BIPUSH 32
    IF_ICMPNE L96
    ICONST_1
    GOTO L97
   L96
    ICONST_0
   L97
    IOR
    ISTORE 14
    NOP
   L98
    ICONST_0
    ISTORE 15
   L99
    LINENUMBER 452 L99
    ALOAD 13
    INVOKEINTERFACE androidx/compose/runtime/Composer.rememberedValue ()Ljava/lang/Object; (itf)
    ASTORE 16
   L100
    ICONST_0
    ISTORE 17
   L101
    LINENUMBER 453 L101
    ILOAD 14
    IFNE L102
    ALOAD 16
    GETSTATIC androidx/compose/runtime/Composer.Companion : Landroidx/compose/runtime/Composer$Companion;
    INVOKEVIRTUAL androidx/compose/runtime/Composer$Companion.getEmpty ()Ljava/lang/Object;
    IF_ACMPNE L103
   L102
    LINENUMBER 454 L102
    NOP
    ASTORE 26
   L104
    ICONST_0
    ISTORE 18
   L105
    LINENUMBER 45 L105
    NEW es/nuskysoftware/marketsales/ui/pantallas/arqueo/PantallaArqueoCajaKt$PantallaArqueoCaja$1$1
    DUP
    ALOAD 7
    ALOAD 1
    ALOAD 10
    ALOAD 11
    ACONST_NULL
    INVOKESPECIAL es/nuskysoftware/marketsales/ui/pantallas/arqueo/PantallaArqueoCajaKt$PantallaArqueoCaja$1$1.<init> (Les/nuskysoftware/marketsales/ui/viewmodel/ArqueoViewModel;Ljava/lang/String;Les/nuskysoftware/marketsales/data/local/database/AppDatabase;Landroidx/compose/runtime/MutableState;Lkotlin/coroutines/Continuation;)V
    CHECKCAST kotlin/jvm/functions/Function2
    NOP
    GOTO L106
   L106
    ASTORE 27
    ALOAD 26
    ALOAD 27
   L107
    LINENUMBER 454 L107
    ASTORE 19
   L108
    LINENUMBER 455 L108
    ALOAD 13
    ALOAD 19
    INVOKEINTERFACE androidx/compose/runtime/Composer.updateRememberedValue (Ljava/lang/Object;)V (itf)
   L109
    LINENUMBER 456 L109
    ALOAD 19
   L110
    GOTO L111
   L103
    LINENUMBER 457 L103
    ALOAD 16
   L111
    LINENUMBER 452 L111
    NOP
   L112
    LINENUMBER 452 L112
    NOP
    GOTO L113
   L113
    LINENUMBER 45 L113
    CHECKCAST kotlin/jvm/functions/Function2
    ASTORE 12
   L114
    ALOAD 2
    INVOKEINTERFACE androidx/compose/runtime/Composer.endReplaceGroup ()V (itf)
    ALOAD 12
   L115
    ALOAD 2
    BIPUSH 14
    ILOAD 4
    ICONST_3
    ISHR
    IAND
    INVOKESTATIC androidx/compose/runtime/EffectsKt.LaunchedEffect (Ljava/lang/Object;Lkotlin/jvm/functions/Function2;Landroidx/compose/runtime/Composer;I)V
    ICONST_0
    ISTORE 14
   L116
    LINENUMBER 52 L116
    NOP
   L117
    ICONST_0
    ISTORE 15
   L118
    ALOAD 2
    LDC 773894976
    LDC "CC(rememberCoroutineScope)N(getContext)608@27648L68:Effects.kt#9igjgp"
   L119
    LINENUMBER 458 L119
    INVOKESTATIC androidx/compose/runtime/ComposerKt.sourceInformationMarkerStart (Landroidx/compose/runtime/Composer;ILjava/lang/String;)V
   L120
    LINENUMBER 459 L120
    ALOAD 2
   L121
    LINENUMBER 463 L121
    ASTORE 16
   L122
    ALOAD 2
    LDC 683737348
    LDC "CC(remember):Effects.kt#9igjgp"
   L123
    LINENUMBER 464 L123
    INVOKESTATIC androidx/compose/runtime/ComposerKt.sourceInformationMarkerStart (Landroidx/compose/runtime/Composer;ILjava/lang/String;)V
    ALOAD 2
    ASTORE 17
    ICONST_0
    ISTORE 18
   L124
    ICONST_0
    ISTORE 19
   L125
    LINENUMBER 465 L125
    ALOAD 17
    INVOKEINTERFACE androidx/compose/runtime/Composer.rememberedValue ()Ljava/lang/Object; (itf)
    ASTORE 20
   L126
    ICONST_0
    ISTORE 21
   L127
    LINENUMBER 466 L127
    ALOAD 20
    GETSTATIC androidx/compose/runtime/Composer.Companion : Landroidx/compose/runtime/Composer$Companion;
    INVOKEVIRTUAL androidx/compose/runtime/Composer$Companion.getEmpty ()Ljava/lang/Object;
    IF_ACMPNE L128
   L129
    LINENUMBER 467 L129
    ICONST_0
    ISTORE 22
   L130
    LINENUMBER 464 L130
    NOP
    ICONST_0
    ISTORE 23
   L131
    NOP
   L132
    LINENUMBER 468 L132
    GETSTATIC kotlin/coroutines/EmptyCoroutineContext.INSTANCE : Lkotlin/coroutines/EmptyCoroutineContext;
    GOTO L133
   L133
    NOP
    GOTO L134
   L134
   L135
    LINENUMBER 464 L135
    CHECKCAST kotlin/coroutines/CoroutineContext
    ALOAD 16
    INVOKESTATIC androidx/compose/runtime/EffectsKt.createCompositionCoroutineScope (Lkotlin/coroutines/CoroutineContext;Landroidx/compose/runtime/Composer;)Lkotlinx/coroutines/CoroutineScope;
   L136
    LINENUMBER 467 L136
    ASTORE 23
   L137
    LINENUMBER 469 L137
    ALOAD 17
    ALOAD 23
    INVOKEINTERFACE androidx/compose/runtime/Composer.updateRememberedValue (Ljava/lang/Object;)V (itf)
   L138
    LINENUMBER 470 L138
    ALOAD 23
   L139
    GOTO L140
   L128
    LINENUMBER 471 L128
    ALOAD 20
   L140
    LINENUMBER 465 L140
    NOP
   L141
    LINENUMBER 465 L141
    NOP
   L142
    LINENUMBER 464 L142
    CHECKCAST kotlinx/coroutines/CoroutineScope
    ASTORE 24
    ALOAD 2
    INVOKESTATIC androidx/compose/runtime/ComposerKt.sourceInformationMarkerEnd (Landroidx/compose/runtime/Composer;)V
    ALOAD 24
    ASTORE 25
    ALOAD 2
   L143
    LINENUMBER 458 L143
    INVOKESTATIC androidx/compose/runtime/ComposerKt.sourceInformationMarkerEnd (Landroidx/compose/runtime/Composer;)V
    ALOAD 25
   L144
    LINENUMBER 464 L144
    NOP
    GOTO L145
   L145
    LINENUMBER 52 L145
    ASTORE 12
   L146
    ALOAD 2
    LDC 1129934555
    INVOKEINTERFACE androidx/compose/runtime/Composer.startReplaceGroup (I)V (itf)
    ALOAD 2
    LDC "CC(remember):PantallaArqueoCaja.kt#9igjgp"
    INVOKESTATIC androidx/compose/runtime/ComposerKt.sourceInformation (Landroidx/compose/runtime/Composer;Ljava/lang/String;)V
    ALOAD 2
    ASTORE 15
    NOP
    ICONST_0
    ISTORE 16
   L147
    LINENUMBER 53 L147
    NOP
   L148
    ICONST_0
    ISTORE 17
   L149
    LINENUMBER 472 L149
    ALOAD 15
    INVOKEINTERFACE androidx/compose/runtime/Composer.rememberedValue ()Ljava/lang/Object; (itf)
    ASTORE 18
   L150
    ICONST_0
    ISTORE 19
   L151
    LINENUMBER 473 L151
    ILOAD 16
    POP
    ALOAD 18
    GETSTATIC androidx/compose/runtime/Composer.Companion : Landroidx/compose/runtime/Composer$Companion;
    INVOKEVIRTUAL androidx/compose/runtime/Composer$Companion.getEmpty ()Ljava/lang/Object;
    IF_ACMPNE L152
   L153
    LINENUMBER 474 L153
    NOP
   L154
    ICONST_0
    ISTORE 20
   L155
    LINENUMBER 53 L155
    ICONST_0
    INVOKESTATIC java/lang/Boolean.valueOf (Z)Ljava/lang/Boolean;
    ACONST_NULL
    ICONST_2
    ACONST_NULL
    INVOKESTATIC androidx/compose/runtime/SnapshotStateKt.mutableStateOf$default (Ljava/lang/Object;Landroidx/compose/runtime/SnapshotMutationPolicy;ILjava/lang/Object;)Landroidx/compose/runtime/MutableState;
    NOP
    GOTO L156
   L156
   L157
    LINENUMBER 474 L157
    ASTORE 20
   L158
    LINENUMBER 475 L158
    ALOAD 15
    ALOAD 20
    INVOKEINTERFACE androidx/compose/runtime/Composer.updateRememberedValue (Ljava/lang/Object;)V (itf)
   L159
    LINENUMBER 476 L159
    ALOAD 20
   L160
    GOTO L161
   L152
    LINENUMBER 477 L152
    ALOAD 18
   L161
    LINENUMBER 472 L161
    NOP
   L162
    LINENUMBER 472 L162
    NOP
    GOTO L163
   L163
    LINENUMBER 53 L163
    CHECKCAST androidx/compose/runtime/MutableState
    ASTORE 14
   L164
    ALOAD 2
    INVOKEINTERFACE androidx/compose/runtime/Composer.endReplaceGroup ()V (itf)
    ALOAD 14
   L165
    ASTORE 13
   L166
    ALOAD 2
    LDC 1129936347
    INVOKEINTERFACE androidx/compose/runtime/Composer.startReplaceGroup (I)V (itf)
    ALOAD 2
    LDC "CC(remember):PantallaArqueoCaja.kt#9igjgp"
    INVOKESTATIC androidx/compose/runtime/ComposerKt.sourceInformation (Landroidx/compose/runtime/Composer;Ljava/lang/String;)V
    ALOAD 2
    ASTORE 16
    NOP
    ICONST_0
    ISTORE 17
   L167
    LINENUMBER 54 L167
    NOP
   L168
    ICONST_0
    ISTORE 18
   L169
    LINENUMBER 478 L169
    ALOAD 16
    INVOKEINTERFACE androidx/compose/runtime/Composer.rememberedValue ()Ljava/lang/Object; (itf)
    ASTORE 19
   L170
    ICONST_0
    ISTORE 20
   L171
    LINENUMBER 479 L171
    ILOAD 17
    POP
    ALOAD 19
    GETSTATIC androidx/compose/runtime/Composer.Companion : Landroidx/compose/runtime/Composer$Companion;
    INVOKEVIRTUAL androidx/compose/runtime/Composer$Companion.getEmpty ()Ljava/lang/Object;
    IF_ACMPNE L172
   L173
    LINENUMBER 480 L173
    NOP
   L174
    ICONST_0
    ISTORE 21
   L175
    LINENUMBER 54 L175
    ICONST_0
    INVOKESTATIC java/lang/Boolean.valueOf (Z)Ljava/lang/Boolean;
    ACONST_NULL
    ICONST_2
    ACONST_NULL
    INVOKESTATIC androidx/compose/runtime/SnapshotStateKt.mutableStateOf$default (Ljava/lang/Object;Landroidx/compose/runtime/SnapshotMutationPolicy;ILjava/lang/Object;)Landroidx/compose/runtime/MutableState;
    NOP
    GOTO L176
   L176
   L177
    LINENUMBER 480 L177
    ASTORE 21
   L178
    LINENUMBER 481 L178
    ALOAD 16
    ALOAD 21
    INVOKEINTERFACE androidx/compose/runtime/Composer.updateRememberedValue (Ljava/lang/Object;)V (itf)
   L179
    LINENUMBER 482 L179
    ALOAD 21
   L180
    GOTO L181
   L172
    LINENUMBER 483 L172
    ALOAD 19
   L181
    LINENUMBER 478 L181
    NOP
   L182
    LINENUMBER 478 L182
    NOP
    GOTO L183
   L183
    LINENUMBER 54 L183
    CHECKCAST androidx/compose/runtime/MutableState
    ASTORE 15
   L184
    ALOAD 2
    INVOKEINTERFACE androidx/compose/runtime/Composer.endReplaceGroup ()V (itf)
    ALOAD 15
   L185
    ASTORE 14
   L186
    ACONST_NULL
   L187
    LINENUMBER 57 L187
    LDC 2030482518
    NOP
    ICONST_1
    NEW es/nuskysoftware/marketsales/ui/pantallas/arqueo/PantallaArqueoCajaKt$PantallaArqueoCaja$2
    DUP
    ALOAD 9
    ALOAD 0
    INVOKESPECIAL es/nuskysoftware/marketsales/ui/pantallas/arqueo/PantallaArqueoCajaKt$PantallaArqueoCaja$2.<init> (Landroidx/compose/runtime/State;Landroidx/navigation/NavController;)V
    ALOAD 2
    BIPUSH 54
    INVOKESTATIC androidx/compose/runtime/internal/ComposableLambdaKt.rememberComposableLambda (IZLjava/lang/Object;Landroidx/compose/runtime/Composer;I)Landroidx/compose/runtime/internal/ComposableLambda;
    CHECKCAST kotlin/jvm/functions/Function2
    ACONST_NULL
    ACONST_NULL
    ACONST_NULL
    ICONST_0
    LCONST_0
    LCONST_0
    ACONST_NULL
   L188
    LINENUMBER 70 L188
    LDC 93278251
    NOP
    ICONST_1
    NEW es/nuskysoftware/marketsales/ui/pantallas/arqueo/PantallaArqueoCajaKt$PantallaArqueoCaja$3
    DUP
    ALOAD 8
    ALOAD 11
    ALOAD 14
    ALOAD 7
    ALOAD 9
    ALOAD 13
    ALOAD 12
    ALOAD 1
    ALOAD 0
    INVOKESPECIAL es/nuskysoftware/marketsales/ui/pantallas/arqueo/PantallaArqueoCajaKt$PantallaArqueoCaja$3.<init> (Landroidx/compose/runtime/State;Landroidx/compose/runtime/MutableState;Landroidx/compose/runtime/MutableState;Les/nuskysoftware/marketsales/ui/viewmodel/ArqueoViewModel;Landroidx/compose/runtime/State;Landroidx/compose/runtime/MutableState;Lkotlinx/coroutines/CoroutineScope;Ljava/lang/String;Landroidx/navigation/NavController;)V
    ALOAD 2
    BIPUSH 54
    INVOKESTATIC androidx/compose/runtime/internal/ComposableLambdaKt.rememberComposableLambda (IZLjava/lang/Object;Landroidx/compose/runtime/Composer;I)Landroidx/compose/runtime/internal/ComposableLambda;
    CHECKCAST kotlin/jvm/functions/Function3
    ALOAD 2
    LDC 805306416
    SIPUSH 509
   L189
    LINENUMBER 56 L189
    INVOKESTATIC androidx/compose/material3/ScaffoldKt.Scaffold-TvnljyQ (Landroidx/compose/ui/Modifier;Lkotlin/jvm/functions/Function2;Lkotlin/jvm/functions/Function2;Lkotlin/jvm/functions/Function2;Lkotlin/jvm/functions/Function2;IJJLandroidx/compose/foundation/layout/WindowInsets;Lkotlin/jvm/functions/Function3;Landroidx/compose/runtime/Composer;II)V
    INVOKESTATIC androidx/compose/runtime/ComposerKt.isTraceInProgress ()Z
    IFEQ L190
    INVOKESTATIC androidx/compose/runtime/ComposerKt.traceEventEnd ()V
   L190
    GOTO L191
   L10
    LINENUMBER 177 L10
    ALOAD 2
    INVOKEINTERFACE androidx/compose/runtime/Composer.skipToGroupEnd ()V (itf)
   L191
    ALOAD 2
    INVOKEINTERFACE androidx/compose/runtime/Composer.endRestartGroup ()Landroidx/compose/runtime/ScopeUpdateScope; (itf)
    ASTORE 5
   L192
    ALOAD 5
    IFNULL L193
    ALOAD 5
    ALOAD 0
    ALOAD 1
    ILOAD 3
    INVOKEDYNAMIC invoke(Landroidx/navigation/NavController;Ljava/lang/String;I)Lkotlin/jvm/functions/Function2; [
      // handle kind 0x6 : INVOKESTATIC
      java/lang/invoke/LambdaMetafactory.metafactory(Ljava/lang/invoke/MethodHandles$Lookup;Ljava/lang/String;Ljava/lang/invoke/MethodType;Ljava/lang/invoke/MethodType;Ljava/lang/invoke/MethodHandle;Ljava/lang/invoke/MethodType;)Ljava/lang/invoke/CallSite;
      // arguments:
      (Ljava/lang/Object;Ljava/lang/Object;)Ljava/lang/Object;, 
      // handle kind 0x6 : INVOKESTATIC
      es/nuskysoftware/marketsales/ui/pantallas/arqueo/PantallaArqueoCajaKt.PantallaArqueoCaja$lambda$14(Landroidx/navigation/NavController;Ljava/lang/String;ILandroidx/compose/runtime/Composer;I)Lkotlin/Unit;, 
      (Landroidx/compose/runtime/Composer;Ljava/lang/Integer;)Lkotlin/Unit;
    ]
    INVOKEINTERFACE androidx/compose/runtime/ScopeUpdateScope.updateScope (Lkotlin/jvm/functions/Function2;)V (itf)
    GOTO L194
   L193
    NOP
   L194
    NOP
    RETURN
   L195
    LOCALVARIABLE $i$f$getCurrent I L13 L15 8
    LOCALVARIABLE this_$iv Landroidx/compose/runtime/CompositionLocal; L12 L15 6
    LOCALVARIABLE $changed$iv I L12 L15 7
    LOCALVARIABLE $i$a$-cache-PantallaArqueoCajaKt$PantallaArqueoCaja$repo$1 I L25 L26 13
    LOCALVARIABLE value$iv Ljava/lang/Object; L28 L30 14
    LOCALVARIABLE $i$a$-let-ComposerKt$cache$1$iv I L21 L31 12
    LOCALVARIABLE it$iv Ljava/lang/Object; L20 L31 11
    LOCALVARIABLE $i$f$cache I L19 L33 10
    LOCALVARIABLE $this$cache$iv Landroidx/compose/runtime/Composer; L18 L33 8
    LOCALVARIABLE invalid$iv Z L18 L33 9
    LOCALVARIABLE $i$a$-checkNotNull-ViewModelKt__ViewModelKt$viewModel$1$iv I L42 L44 14
    LOCALVARIABLE $i$f$viewModel I L38 L52 13
    LOCALVARIABLE viewModelStoreOwner$iv Landroidx/lifecycle/ViewModelStoreOwner; L45 L52 8
    LOCALVARIABLE key$iv Ljava/lang/String; L46 L52 9
    LOCALVARIABLE factory$iv Landroidx/lifecycle/ViewModelProvider$Factory; L37 L52 10
    LOCALVARIABLE extras$iv Landroidx/lifecycle/viewmodel/CreationExtras; L50 L52 11
    LOCALVARIABLE $changed$iv I L37 L52 12
    LOCALVARIABLE $i$a$-cache-PantallaArqueoCajaKt$PantallaArqueoCaja$db$1 I L64 L65 17
    LOCALVARIABLE value$iv Ljava/lang/Object; L67 L69 18
    LOCALVARIABLE $i$a$-let-ComposerKt$cache$1$iv I L60 L70 16
    LOCALVARIABLE it$iv Ljava/lang/Object; L59 L70 15
    LOCALVARIABLE $i$f$cache I L58 L72 14
    LOCALVARIABLE $this$cache$iv Landroidx/compose/runtime/Composer; L57 L72 12
    LOCALVARIABLE invalid$iv Z L57 L72 13
    LOCALVARIABLE $i$a$-cache-PantallaArqueoCajaKt$PantallaArqueoCaja$gastosEfectivo$2 I L84 L85 18
    LOCALVARIABLE value$iv Ljava/lang/Object; L87 L89 18
    LOCALVARIABLE $i$a$-let-ComposerKt$cache$1$iv I L80 L90 17
    LOCALVARIABLE it$iv Ljava/lang/Object; L79 L90 16
    LOCALVARIABLE $i$f$cache I L78 L92 15
    LOCALVARIABLE $this$cache$iv Landroidx/compose/runtime/Composer; L77 L92 13
    LOCALVARIABLE invalid$iv Z L77 L92 14
    LOCALVARIABLE $i$a$-cache-PantallaArqueoCajaKt$PantallaArqueoCaja$1 I L105 L106 18
    LOCALVARIABLE value$iv Ljava/lang/Object; L108 L110 19
    LOCALVARIABLE $i$a$-let-ComposerKt$cache$1$iv I L101 L111 17
    LOCALVARIABLE it$iv Ljava/lang/Object; L100 L111 16
    LOCALVARIABLE $i$f$cache I L99 L113 15
    LOCALVARIABLE $this$cache$iv Landroidx/compose/runtime/Composer; L98 L113 13
    LOCALVARIABLE invalid$iv Z L98 L113 14
    LOCALVARIABLE $i$a$-rememberCoroutineScope-EffectsKt$rememberCoroutineScope$1 I L131 L134 23
    LOCALVARIABLE $i$a$-cache-EffectsKt$rememberCoroutineScope$2$iv I L130 L136 22
    LOCALVARIABLE value$iv$iv Ljava/lang/Object; L137 L139 23
    LOCALVARIABLE $i$a$-let-ComposerKt$cache$1$iv$iv I L127 L140 21
    LOCALVARIABLE it$iv$iv Ljava/lang/Object; L126 L140 20
    LOCALVARIABLE $i$f$cache I L125 L142 19
    LOCALVARIABLE $this$cache$iv$iv Landroidx/compose/runtime/Composer; L124 L142 17
    LOCALVARIABLE invalid$iv$iv Z L124 L142 18
    LOCALVARIABLE $i$f$rememberCoroutineScope I L118 L145 15
    LOCALVARIABLE composer$iv Landroidx/compose/runtime/Composer; L122 L145 16
    LOCALVARIABLE $changed$iv I L117 L145 14
    LOCALVARIABLE $i$a$-cache-PantallaArqueoCajaKt$PantallaArqueoCaja$mostrarDialogo$2 I L155 L156 20
    LOCALVARIABLE value$iv Ljava/lang/Object; L158 L160 20
    LOCALVARIABLE $i$a$-let-ComposerKt$cache$1$iv I L151 L161 19
    LOCALVARIABLE it$iv Ljava/lang/Object; L150 L161 18
    LOCALVARIABLE $i$f$cache I L149 L163 17
    LOCALVARIABLE $this$cache$iv Landroidx/compose/runtime/Composer; L148 L163 15
    LOCALVARIABLE invalid$iv Z L148 L163 16
    LOCALVARIABLE $i$a$-cache-PantallaArqueoCajaKt$PantallaArqueoCaja$guardando$2 I L175 L176 21
    LOCALVARIABLE value$iv Ljava/lang/Object; L178 L180 21
    LOCALVARIABLE $i$a$-let-ComposerKt$cache$1$iv I L171 L181 20
    LOCALVARIABLE it$iv Ljava/lang/Object; L170 L181 19
    LOCALVARIABLE $i$f$cache I L169 L183 18
    LOCALVARIABLE $this$cache$iv Landroidx/compose/runtime/Composer; L168 L183 16
    LOCALVARIABLE invalid$iv Z L168 L183 17
    LOCALVARIABLE context Landroid/content/Context; L16 L190 5
    LOCALVARIABLE repo Les/nuskysoftware/marketsales/data/repository/MercadilloRepository; L36 L190 6
    LOCALVARIABLE vm Les/nuskysoftware/marketsales/ui/viewmodel/ArqueoViewModel; L53 L190 7
    LOCALVARIABLE ui$delegate Landroidx/compose/runtime/State; L54 L190 8
    LOCALVARIABLE currentLanguage$delegate Landroidx/compose/runtime/State; L55 L190 9
    LOCALVARIABLE db Les/nuskysoftware/marketsales/data/local/database/AppDatabase; L75 L190 10
    LOCALVARIABLE gastosEfectivo$delegate Landroidx/compose/runtime/MutableState; L95 L190 11
    LOCALVARIABLE scope Lkotlinx/coroutines/CoroutineScope; L146 L190 12
    LOCALVARIABLE mostrarDialogo$delegate Landroidx/compose/runtime/MutableState; L166 L190 13
    LOCALVARIABLE guardando$delegate Landroidx/compose/runtime/MutableState; L186 L190 14
    LOCALVARIABLE $dirty I L2 L195 4
    LOCALVARIABLE navController Landroidx/navigation/NavController; L0 L195 0
    LOCALVARIABLE mercadilloId Ljava/lang/String; L0 L195 1
    LOCALVARIABLE $composer Landroidx/compose/runtime/Composer; L0 L195 2
    LOCALVARIABLE $changed I L0 L195 3
    MAXSTACK = 24
    MAXLOCALS = 28

File is unknown
The root cause java.lang.OutOfMemoryError was thrown at: org.jetbrains.org.objectweb.asm.tree.analysis.Frame.<init>(Frame.java:78)
	at org.jetbrains.kotlin.codegen.TransformationMethodVisitor.visitEnd(TransformationMethodVisitor.kt:89)
	at org.jetbrains.org.objectweb.asm.MethodVisitor.visitEnd(MethodVisitor.java:783)
	at org.jetbrains.org.objectweb.asm.tree.MethodNode.accept(MethodNode.java:772)
	at org.jetbrains.kotlin.backend.jvm.codegen.ClassCodegen.generateMethod(ClassCodegen.kt:453)
	at org.jetbrains.kotlin.backend.jvm.codegen.ClassCodegen.generate(ClassCodegen.kt:168)
	at org.jetbrains.kotlin.backend.jvm.FileCodegen.lower(JvmPhases.kt:39)
	at org.jetbrains.kotlin.backend.common.phaser.PhaseFactoriesKt.createFilePhase$lambda$4(PhaseFactories.kt:71)
	at org.jetbrains.kotlin.backend.common.phaser.PhaseBuildersKt$createSimpleNamedCompilerPhase$1.phaseBody(PhaseBuilders.kt:69)
	at org.jetbrains.kotlin.backend.common.phaser.SimpleNamedCompilerPhase.phaseBody(CompilerPhase.kt:226)
	at org.jetbrains.kotlin.backend.common.phaser.AbstractNamedCompilerPhase.invoke(CompilerPhase.kt:113)
	at org.jetbrains.kotlin.backend.common.phaser.PerformByIrFilePhase.invokeSequential(performByIrFile.kt:62)
	at org.jetbrains.kotlin.backend.common.phaser.PerformByIrFilePhase.invoke(performByIrFile.kt:52)
	at org.jetbrains.kotlin.backend.common.phaser.PerformByIrFilePhase.invoke(performByIrFile.kt:38)
	at org.jetbrains.kotlin.backend.common.phaser.NamedCompilerPhase.phaseBody(CompilerPhase.kt:166)
	at org.jetbrains.kotlin.backend.common.phaser.AbstractNamedCompilerPhase.invoke(CompilerPhase.kt:113)
	at org.jetbrains.kotlin.backend.common.phaser.CompositePhase.invoke(PhaseBuilders.kt:27)
	at org.jetbrains.kotlin.backend.common.phaser.CompositePhase.invoke(PhaseBuilders.kt:14)
	at org.jetbrains.kotlin.backend.common.phaser.NamedCompilerPhase.phaseBody(CompilerPhase.kt:166)
	at org.jetbrains.kotlin.backend.common.phaser.AbstractNamedCompilerPhase.invoke(CompilerPhase.kt:113)
	at org.jetbrains.kotlin.backend.common.phaser.CompilerPhaseKt.invokeToplevel(CompilerPhase.kt:62)
	at org.jetbrains.kotlin.backend.jvm.JvmIrCodegenFactory.invokeCodegen(JvmIrCodegenFactory.kt:371)
	at org.jetbrains.kotlin.codegen.CodegenFactory.generateModule(CodegenFactory.kt:47)
	at org.jetbrains.kotlin.backend.jvm.JvmIrCodegenFactory.generateModuleInFrontendIRMode(JvmIrCodegenFactory.kt:433)
	at org.jetbrains.kotlin.cli.jvm.compiler.pipeline.JvmCompilerPipelineKt.generateCodeFromIr(jvmCompilerPipeline.kt:246)
	at org.jetbrains.kotlin.cli.jvm.compiler.pipeline.JvmCompilerPipelineKt.compileModulesUsingFrontendIrAndLightTree(jvmCompilerPipeline.kt:142)
	at org.jetbrains.kotlin.cli.jvm.K2JVMCompiler.doExecute(K2JVMCompiler.kt:148)
	at org.jetbrains.kotlin.cli.jvm.K2JVMCompiler.doExecute(K2JVMCompiler.kt:43)
	at org.jetbrains.kotlin.cli.common.CLICompiler.execImpl(CLICompiler.kt:103)
	at org.jetbrains.kotlin.cli.common.CLICompiler.execImpl(CLICompiler.kt:49)
	at org.jetbrains.kotlin.cli.common.CLITool.exec(CLITool.kt:101)
	at org.jetbrains.kotlin.incremental.IncrementalJvmCompilerRunner.runCompiler(IncrementalJvmCompilerRunner.kt:464)
	at org.jetbrains.kotlin.incremental.IncrementalJvmCompilerRunner.runCompiler(IncrementalJvmCompilerRunner.kt:73)
	at org.jetbrains.kotlin.incremental.IncrementalCompilerRunner.doCompile(IncrementalCompilerRunner.kt:506)
	at org.jetbrains.kotlin.incremental.IncrementalCompilerRunner.compileImpl(IncrementalCompilerRunner.kt:423)
	at org.jetbrains.kotlin.incremental.IncrementalCompilerRunner.compileNonIncrementally(IncrementalCompilerRunner.kt:301)
	at org.jetbrains.kotlin.incremental.IncrementalCompilerRunner.compile(IncrementalCompilerRunner.kt:129)
	at org.jetbrains.kotlin.daemon.CompileServiceImplBase.execIncrementalCompiler(CompileServiceImpl.kt:675)
	at org.jetbrains.kotlin.daemon.CompileServiceImplBase.access$execIncrementalCompiler(CompileServiceImpl.kt:92)
	at org.jetbrains.kotlin.daemon.CompileServiceImpl.compile(CompileServiceImpl.kt:1660)
	at java.base/jdk.internal.reflect.DirectMethodHandleAccessor.invoke(Unknown Source)
	at java.base/java.lang.reflect.Method.invoke(Unknown Source)
	at java.rmi/sun.rmi.server.UnicastServerRef.dispatch(Unknown Source)
	at java.rmi/sun.rmi.transport.Transport$1.run(Unknown Source)
	at java.rmi/sun.rmi.transport.Transport$1.run(Unknown Source)
	at java.base/java.security.AccessController.doPrivileged(Unknown Source)
	at java.rmi/sun.rmi.transport.Transport.serviceCall(Unknown Source)
	at java.rmi/sun.rmi.transport.tcp.TCPTransport.handleMessages(Unknown Source)
	at java.rmi/sun.rmi.transport.tcp.TCPTransport$ConnectionHandler.run0(Unknown Source)
	at java.rmi/sun.rmi.transport.tcp.TCPTransport$ConnectionHandler.lambda$run$0(Unknown Source)
	at java.base/java.security.AccessController.doPrivileged(Unknown Source)
	at java.rmi/sun.rmi.transport.tcp.TCPTransport$ConnectionHandler.run(Unknown Source)
	at java.base/java.util.concurrent.ThreadPoolExecutor.runWorker(Unknown Source)
	at java.base/java.util.concurrent.ThreadPoolExecutor$Worker.run(Unknown Source)
	at java.base/java.lang.Thread.run(Unknown Source)
Caused by: java.lang.OutOfMemoryError: GC overhead limit exceeded
	at org.jetbrains.org.objectweb.asm.tree.analysis.Frame.<init>(Frame.java:78)
	at org.jetbrains.kotlin.codegen.optimization.common.FastMethodAnalyzer._init_$lambda$0(FastMethodAnalyzer.kt:47)
	at org.jetbrains.kotlin.codegen.optimization.common.FastMethodAnalyzer$$Lambda/0x000000010115d798.invoke(Unknown Source)
	at org.jetbrains.kotlin.codegen.optimization.common.FastAnalyzer.fullMergeControlFlowEdge(FastAnalyzer.kt:233)
	at org.jetbrains.kotlin.codegen.optimization.common.FastAnalyzer.mergeControlFlowEdge(FastAnalyzer.kt:216)
	at org.jetbrains.kotlin.codegen.optimization.common.FastAnalyzer.processControlFlowEdge(FastAnalyzer.kt:208)
	at org.jetbrains.kotlin.codegen.optimization.common.FastAnalyzer.processControlFlowEdge$default(FastAnalyzer.kt:206)
	at org.jetbrains.kotlin.codegen.optimization.common.FastAnalyzer.visitOpInsn(FastAnalyzer.kt:292)
	at org.jetbrains.kotlin.codegen.optimization.common.FastAnalyzer.visitMeaningfulInstruction(FastAnalyzer.kt:281)
	at org.jetbrains.kotlin.codegen.optimization.common.FastAnalyzer.analyzeInstruction(FastAnalyzer.kt:113)
	at org.jetbrains.kotlin.codegen.optimization.common.FastAnalyzer.analyzeMainLoop(FastAnalyzer.kt:74)
	at org.jetbrains.kotlin.codegen.optimization.common.FastAnalyzer.analyze(FastAnalyzer.kt:53)
	at org.jetbrains.kotlin.codegen.optimization.transformer.MethodTransformer.analyze(MethodTransformer.java:49)
	at org.jetbrains.kotlin.codegen.optimization.ConstantConditionEliminationMethodTransformer$ConstantConditionsOptimization.collectRewriteActions(ConstantConditionEliminationMethodTransformer.kt:65)
	at org.jetbrains.kotlin.codegen.optimization.ConstantConditionEliminationMethodTransformer$ConstantConditionsOptimization.run(ConstantConditionEliminationMethodTransformer.kt:56)
	at org.jetbrains.kotlin.codegen.optimization.ConstantConditionEliminationMethodTransformer.transform(ConstantConditionEliminationMethodTransformer.kt:39)
	at org.jetbrains.kotlin.codegen.optimization.transformer.CompositeMethodTransformer.transform(CompositeMethodTransformer.kt:25)
	at org.jetbrains.kotlin.codegen.optimization.OptimizationMethodVisitor.performTransformations(OptimizationMethodVisitor.kt:74)
	at org.jetbrains.kotlin.codegen.TransformationMethodVisitor.visitEnd(TransformationMethodVisitor.kt:67)
	at org.jetbrains.org.objectweb.asm.MethodVisitor.visitEnd(MethodVisitor.java:783)
	at org.jetbrains.org.objectweb.asm.tree.MethodNode.accept(MethodNode.java:772)
	at org.jetbrains.kotlin.backend.jvm.codegen.ClassCodegen.generateMethod(ClassCodegen.kt:453)
	at org.jetbrains.kotlin.backend.jvm.codegen.ClassCodegen.generate(ClassCodegen.kt:168)
	at org.jetbrains.kotlin.backend.jvm.FileCodegen.lower(JvmPhases.kt:39)
	at org.jetbrains.kotlin.backend.common.phaser.PhaseFactoriesKt.createFilePhase$lambda$4(PhaseFactories.kt:71)
	at org.jetbrains.kotlin.backend.common.phaser.PhaseFactoriesKt$$Lambda/0x00000001002265d0.invoke(Unknown Source)
	at org.jetbrains.kotlin.backend.common.phaser.PhaseBuildersKt$createSimpleNamedCompilerPhase$1.phaseBody(PhaseBuilders.kt:69)
	at org.jetbrains.kotlin.backend.common.phaser.SimpleNamedCompilerPhase.phaseBody(CompilerPhase.kt:226)
	at org.jetbrains.kotlin.backend.common.phaser.AbstractNamedCompilerPhase.invoke(CompilerPhase.kt:113)
	at org.jetbrains.kotlin.backend.common.phaser.PerformByIrFilePhase.invokeSequential(performByIrFile.kt:62)
	at org.jetbrains.kotlin.backend.common.phaser.PerformByIrFilePhase.invoke(performByIrFile.kt:52)
	at org.jetbrains.kotlin.backend.common.phaser.PerformByIrFilePhase.invoke(performByIrFile.kt:38)


